Metadata-Version: 2.1
Name: lib-dzne-masterfile
Version: 0.1.0
Summary: Libary for handling the manifesto. 
Author-email: Johannes Horler <johannes.horler@dzne.de>
License: Copyright © 2022 Johannes Horler
Classifier: License :: OSI Approved :: MIT License
Classifier: Programming Language :: Python
Classifier: Programming Language :: Python :: 3
Requires-Python: >=3.11
License-File: LICENSE
Requires-Dist: pandas (>=1.4.2)
Requires-Dist: lib-dzne-manifesto (>=0.1.0)
Requires-Dist: lib-dzne-workbook (>=0.1.3)
Requires-Dist: lib-dzne-sqlite (>=0.1.1)
Requires-Dist: lib-dzne-data (>=0.1.2)
